GoogleJavaBianchengGuifan/README.md
GoogleJavaBianchengGuifan/__init__.py
GoogleJavaBianchengGuifan/__main__.py
GoogleJavaBianchengGuifan/file.epub
GoogleJavaBianchengGuifan/index.html
GoogleJavaBianchengGuifan/css/__init__.py
GoogleJavaBianchengGuifan/css/annotations.css
GoogleJavaBianchengGuifan/css/main.css
GoogleJavaBianchengGuifan/css/normalize.css
GoogleJavaBianchengGuifan/css/popup.css
GoogleJavaBianchengGuifan/font/__init__.py
GoogleJavaBianchengGuifan/font/fontello.eot
GoogleJavaBianchengGuifan/font/fontello.svg
GoogleJavaBianchengGuifan/font/fontello.ttf
GoogleJavaBianchengGuifan/font/fontello.woff
GoogleJavaBianchengGuifan/img/__init__.py
GoogleJavaBianchengGuifan/img/annotator-glyph-sprite.png
GoogleJavaBianchengGuifan/img/annotator-icon-sprite.png
GoogleJavaBianchengGuifan/img/apple-touch-icon.png
GoogleJavaBianchengGuifan/img/cancelfullscreen.png
GoogleJavaBianchengGuifan/img/close.png
GoogleJavaBianchengGuifan/img/fullscreen.png
GoogleJavaBianchengGuifan/img/loader.gif
GoogleJavaBianchengGuifan/img/menu-icon.png
GoogleJavaBianchengGuifan/img/save.png
GoogleJavaBianchengGuifan/img/saved.png
GoogleJavaBianchengGuifan/img/settings-s.png
GoogleJavaBianchengGuifan/img/settings.png
GoogleJavaBianchengGuifan/img/star.png
GoogleJavaBianchengGuifan/js/__init__.py
GoogleJavaBianchengGuifan/js/epub.js
GoogleJavaBianchengGuifan/js/epub.min.js
GoogleJavaBianchengGuifan/js/epub.min.map
GoogleJavaBianchengGuifan/js/hooks.min.js
GoogleJavaBianchengGuifan/js/hooks.min.map
GoogleJavaBianchengGuifan/js/reader.js
GoogleJavaBianchengGuifan/js/reader.js.map
GoogleJavaBianchengGuifan/js/reader.min.js
GoogleJavaBianchengGuifan/js/reader.min.map
GoogleJavaBianchengGuifan/js/hooks/__init__.py
GoogleJavaBianchengGuifan/js/hooks/extensions/__init__.py
GoogleJavaBianchengGuifan/js/hooks/extensions/highlight.js
GoogleJavaBianchengGuifan/js/libs/__init__.py
GoogleJavaBianchengGuifan/js/libs/jquery.min.js
GoogleJavaBianchengGuifan/js/libs/localforage.min.js
google_java_biancheng_guifan-2024.3.1.0.dist-info/METADATA
google_java_biancheng_guifan-2024.3.1.0.dist-info/WHEEL
google_java_biancheng_guifan-2024.3.1.0.dist-info/entry_points.txt
google_java_biancheng_guifan-2024.3.1.0.dist-info/top_level.txt
google_java_biancheng_guifan-2024.3.1.0.dist-info/RECORD
